velox/__init__.py
velox/core/__init__.py
velox/core/context.py
velox/core/engine.py
velox/core/pipeline.py
velox/layers/__init__.py
velox/layers/advanced_dashboard.py
velox/layers/auto_tooling.py
velox/layers/base.py
velox/layers/caching.py
velox/layers/cost_optimizer.py
velox/layers/dashboard.py
velox/layers/logging.py
velox/layers/pii_guard.py
velox/layers/resilience.py
velox/layers/semantic_router.py
velox/layers/shadow.py
velox/providers/__init__.py
velox/providers/anthropic.py
velox/providers/base.py
velox/providers/google.py
velox/providers/groq.py
velox/providers/mistral.py
velox/providers/mock.py
velox/providers/openai.py
velox_core-0.1.0.dist-info/METADATA
velox_core-0.1.0.dist-info/WHEEL
velox_core-0.1.0.dist-info/RECORD
