Metadata-Version: 2.4
Name: velox-core
Version: 0.1.0
Summary: High-Performance Middleware Engine for LLMs
Project-URL: Homepage, https://github.com/example/velox-core
Author-email: Zied Boughdir <ZiedBoughdir@gmail.com>
License: MIT
Requires-Python: >=3.9
Requires-Dist: colorama>=0.4.6
Requires-Dist: google-generativeai>=0.5.0
Requires-Dist: httpx>=0.24.0
Requires-Dist: openai>=1.0.0
Requires-Dist: pydantic>=2.0.0
Requires-Dist: rich>=13.0.0
